<?xml version="1.0" encoding="UTF-8"?>
<issues format="6" by="lint 9.2.0" type="baseline" client="gradle" dependencies="false" name="AGP (9.2.0)" variant="all" version="9.2.0">

    <issue
        id="MissingPermission"
        message="Call requires permission which may be rejected by user: code should explicitly check to see if permission is available (with `checkPermission`) or explicitly handle a potential `SecurityException`"
        errorLine1="        NotificationManagerCompat.from(context).notify(NOTIFICATION_ID, notification)"
        errorLine2="        ~~~~~~~~~~~~~~~~~~~~~~~~~~~~~~~~~~~~~~~~~~~~~~~~~~~~~~~~~~~~~~~~~~~~~~~~~~~~~">
        <location
            file="src/main/java/com/tenebris/health_tracker/data/service/CoachNotificationDispatcher.kt"
            line="71"
            column="9"/>
    </issue>

    <issue
        id="MissingPermission"
        message="Missing permissions required by Vibrator.vibrate: android.permission.VIBRATE"
        errorLine1="            vibrator?.vibrate(pattern)"
        errorLine2="            ~~~~~~~~~~~~~~~~~~~~~~~~~~">
        <location
            file="src/main/java/com/tenebris/health_tracker/data/service/CoachNotificationDispatcher.kt"
            line="91"
            column="13"/>
    </issue>

    <issue
        id="OldTargetApi"
        message="Not targeting the latest versions of Android; compatibility modes apply. Consider testing and updating this version. Consult the `android.os.Build.VERSION_CODES` javadoc for details."
        errorLine1="        targetSdk = 36"
        errorLine2="        ~~~~~~~~~~~~~~">
        <location
            file="build.gradle.kts"
            line="24"
            column="9"/>
    </issue>

    <issue
        id="RedundantLabel"
        message="Redundant label can be removed"
        errorLine1="            android:label=&quot;@string/app_name&quot;"
        errorLine2="            ~~~~~~~~~~~~~~~~~~~~~~~~~~~~~~~~">
        <location
            file="src/main/AndroidManifest.xml"
            line="29"
            column="13"/>
    </issue>

    <issue
        id="AndroidGradlePluginVersion"
        message="A newer version of Gradle than 9.4.1 is available: 9.5.1"
        errorLine1="distributionUrl=https\://services.gradle.org/distributions/gradle-9.4.1-bin.zip"
        errorLine2="                ~~~~~~~~~~~~~~~~~~~~~~~~~~~~~~~~~~~~~~~~~~~~~~~~~~~~~~~~~~~~~~~">
        <location
            file="$HOME/StudioProjects/Calorie-Tracker/gradle/wrapper/gradle-wrapper.properties"
            line="5"
            column="17"/>
    </issue>

    <issue
        id="AndroidGradlePluginVersion"
        message="A newer version of com.android.application than 9.2.0 is available: 9.2.1"
        errorLine1="agp = &quot;9.2.0&quot;"
        errorLine2="      ~~~~~~~">
        <location
            file="$HOME/StudioProjects/Calorie-Tracker/gradle/libs.versions.toml"
            line="2"
            column="7"/>
    </issue>

    <issue
        id="AndroidGradlePluginVersion"
        message="A newer version of com.android.test than 9.2.0 is available: 9.2.1"
        errorLine1="agp = &quot;9.2.0&quot;"
        errorLine2="      ~~~~~~~">
        <location
            file="$HOME/StudioProjects/Calorie-Tracker/gradle/libs.versions.toml"
            line="2"
            column="7"/>
    </issue>

    <issue
        id="GradleDependency"
        message="A newer version of `compileSdk` than 36 is available: 37"
        errorLine1="            release(36) {"
        errorLine2="            ^">
        <location
            file="build.gradle.kts"
            line="16"
            column="13"/>
    </issue>

    <issue
        id="GradleDependency"
        message="A newer version of androidx.core:core-ktx than 1.10.1 is available: 1.19.0"
        errorLine1="coreKtx = &quot;1.10.1&quot;"
        errorLine2="          ~~~~~~~~">
        <location
            file="$HOME/StudioProjects/Calorie-Tracker/gradle/libs.versions.toml"
            line="4"
            column="11"/>
    </issue>

    <issue
        id="GradleDependency"
        message="A newer version of androidx.test.ext:junit than 1.1.5 is available: 1.3.0"
        errorLine1="junitVersion = &quot;1.1.5&quot;"
        errorLine2="               ~~~~~~~">
        <location
            file="$HOME/StudioProjects/Calorie-Tracker/gradle/libs.versions.toml"
            line="6"
            column="16"/>
    </issue>

    <issue
        id="GradleDependency"
        message="A newer version of androidx.test.espresso:espresso-core than 3.5.1 is available: 3.7.0"
        errorLine1="espressoCore = &quot;3.5.1&quot;"
        errorLine2="               ~~~~~~~">
        <location
            file="$HOME/StudioProjects/Calorie-Tracker/gradle/libs.versions.toml"
            line="7"
            column="16"/>
    </issue>

    <issue
        id="GradleDependency"
        message="A newer version of androidx.lifecycle:lifecycle-runtime-ktx than 2.6.1 is available: 2.10.0"
        errorLine1="lifecycleRuntimeKtx = &quot;2.6.1&quot;"
        errorLine2="                      ~~~~~~~">
        <location
            file="$HOME/StudioProjects/Calorie-Tracker/gradle/libs.versions.toml"
            line="8"
            column="23"/>
    </issue>

    <issue
        id="GradleDependency"
        message="A newer version of androidx.activity:activity-compose than 1.8.0 is available: 1.13.0"
        errorLine1="activityCompose = &quot;1.8.0&quot;"
        errorLine2="                  ~~~~~~~">
        <location
            file="$HOME/StudioProjects/Calorie-Tracker/gradle/libs.versions.toml"
            line="9"
            column="19"/>
    </issue>

    <issue
        id="GradleDependency"
        message="A newer version of androidx.compose:compose-bom than 2026.02.01 is available: 2026.05.01"
        errorLine1="composeBom = &quot;2026.02.01&quot;"
        errorLine2="             ~~~~~~~~~~~~">
        <location
            file="$HOME/StudioProjects/Calorie-Tracker/gradle/libs.versions.toml"
            line="11"
            column="14"/>
    </issue>

    <issue
        id="GradleDependency"
        message="A newer version of androidx.compose.material3:material3 than 1.5.0-alpha11 is available: 1.5.0-alpha21"
        errorLine1="material3 = &quot;1.5.0-alpha11&quot;"
        errorLine2="            ~~~~~~~~~~~~~~~">
        <location
            file="$HOME/StudioProjects/Calorie-Tracker/gradle/libs.versions.toml"
            line="12"
            column="13"/>
    </issue>

    <issue
        id="GradleDependency"
        message="A newer version of androidx.compose.material3:material3-adaptive-navigation-suite than 1.5.0-alpha11 is available: 1.5.0-alpha21"
        errorLine1="material3AdaptiveNavigationSuite = &quot;1.5.0-alpha11&quot;"
        errorLine2="                                   ~~~~~~~~~~~~~~~">
        <location
            file="$HOME/StudioProjects/Calorie-Tracker/gradle/libs.versions.toml"
            line="13"
            column="36"/>
    </issue>

    <issue
        id="GradleDependency"
        message="A newer version of androidx.room:room-compiler than 2.7.0-beta01 is available: 2.8.4"
        errorLine1="room = &quot;2.7.0-beta01&quot;"
        errorLine2="       ~~~~~~~~~~~~~~">
        <location
            file="$HOME/StudioProjects/Calorie-Tracker/gradle/libs.versions.toml"
            line="14"
            column="8"/>
    </issue>

    <issue
        id="GradleDependency"
        message="A newer version of androidx.room:room-ktx than 2.7.0-beta01 is available: 2.8.4"
        errorLine1="room = &quot;2.7.0-beta01&quot;"
        errorLine2="       ~~~~~~~~~~~~~~">
        <location
            file="$HOME/StudioProjects/Calorie-Tracker/gradle/libs.versions.toml"
            line="14"
            column="8"/>
    </issue>

    <issue
        id="GradleDependency"
        message="A newer version of androidx.room:room-runtime than 2.7.0-beta01 is available: 2.8.4"
        errorLine1="room = &quot;2.7.0-beta01&quot;"
        errorLine2="       ~~~~~~~~~~~~~~">
        <location
            file="$HOME/StudioProjects/Calorie-Tracker/gradle/libs.versions.toml"
            line="14"
            column="8"/>
    </issue>

    <issue
        id="GradleDependency"
        message="A newer version of androidx.datastore:datastore-preferences than 1.1.1 is available: 1.2.1"
        errorLine1="datastore = &quot;1.1.1&quot;"
        errorLine2="            ~~~~~~~">
        <location
            file="$HOME/StudioProjects/Calorie-Tracker/gradle/libs.versions.toml"
            line="15"
            column="13"/>
    </issue>

    <issue
        id="GradleDependency"
        message="A newer version of androidx.navigation:navigation-compose than 2.8.5 is available: 2.9.8"
        errorLine1="navigation = &quot;2.8.5&quot;"
        errorLine2="             ~~~~~~~">
        <location
            file="$HOME/StudioProjects/Calorie-Tracker/gradle/libs.versions.toml"
            line="16"
            column="14"/>
    </issue>

    <issue
        id="GradleDependency"
        message="A newer version of androidx.lifecycle:lifecycle-runtime-compose than 2.8.7 is available: 2.10.0"
        errorLine1="lifecycle = &quot;2.8.7&quot;"
        errorLine2="            ~~~~~~~">
        <location
            file="$HOME/StudioProjects/Calorie-Tracker/gradle/libs.versions.toml"
            line="17"
            column="13"/>
    </issue>

    <issue
        id="GradleDependency"
        message="A newer version of androidx.lifecycle:lifecycle-viewmodel-compose than 2.8.7 is available: 2.10.0"
        errorLine1="lifecycle = &quot;2.8.7&quot;"
        errorLine2="            ~~~~~~~">
        <location
            file="$HOME/StudioProjects/Calorie-Tracker/gradle/libs.versions.toml"
            line="17"
            column="13"/>
    </issue>

    <issue
        id="GradleDependency"
        message="A newer version of org.jetbrains.kotlinx:kotlinx-serialization-json than 1.8.0 is available: 1.8.1"
        errorLine1="kotlinx-serialization = &quot;1.8.0&quot;"
        errorLine2="                        ~~~~~~~">
        <location
            file="$HOME/StudioProjects/Calorie-Tracker/gradle/libs.versions.toml"
            line="21"
            column="25"/>
    </issue>

    <issue
        id="GradleDependency"
        message="A newer version of androidx.camera:camera-camera2 than 1.6.0 is available: 1.6.1"
        errorLine1="camerax = &quot;1.6.0&quot;"
        errorLine2="          ~~~~~~~">
        <location
            file="$HOME/StudioProjects/Calorie-Tracker/gradle/libs.versions.toml"
            line="24"
            column="11"/>
    </issue>

    <issue
        id="GradleDependency"
        message="A newer version of androidx.camera:camera-lifecycle than 1.6.0 is available: 1.6.1"
        errorLine1="camerax = &quot;1.6.0&quot;"
        errorLine2="          ~~~~~~~">
        <location
            file="$HOME/StudioProjects/Calorie-Tracker/gradle/libs.versions.toml"
            line="24"
            column="11"/>
    </issue>

    <issue
        id="GradleDependency"
        message="A newer version of androidx.camera:camera-view than 1.6.0 is available: 1.6.1"
        errorLine1="camerax = &quot;1.6.0&quot;"
        errorLine2="          ~~~~~~~">
        <location
            file="$HOME/StudioProjects/Calorie-Tracker/gradle/libs.versions.toml"
            line="24"
            column="11"/>
    </issue>

    <issue
        id="GradleDependency"
        message="A newer version of androidx.work:work-runtime-ktx than 2.10.0 is available: 2.11.2"
        errorLine1="workmanager = &quot;2.10.0&quot;"
        errorLine2="              ~~~~~~~~">
        <location
            file="$HOME/StudioProjects/Calorie-Tracker/gradle/libs.versions.toml"
            line="26"
            column="15"/>
    </issue>

    <issue
        id="GradleDependency"
        message="A newer version of androidx.security:security-crypto than 1.1.0-alpha06 is available: 1.1.0"
        errorLine1="security-crypto = &quot;1.1.0-alpha06&quot;"
        errorLine2="                  ~~~~~~~~~~~~~~~">
        <location
            file="$HOME/StudioProjects/Calorie-Tracker/gradle/libs.versions.toml"
            line="27"
            column="19"/>
    </issue>

    <issue
        id="GradleDependency"
        message="A newer version of androidx.benchmark:benchmark-macro-junit4 than 1.3.3 is available: 1.4.1"
        errorLine1="benchmark = &quot;1.3.3&quot;"
        errorLine2="            ~~~~~~~">
        <location
            file="$HOME/StudioProjects/Calorie-Tracker/gradle/libs.versions.toml"
            line="31"
            column="13"/>
    </issue>

    <issue
        id="GradleDependency"
        message="A newer version of androidx.core:core-splashscreen than 1.0.1 is available: 1.2.0"
        errorLine1="androidx-core-splashscreen = { group = &quot;androidx.core&quot;, name = &quot;core-splashscreen&quot;, version = &quot;1.0.1&quot; }"
        errorLine2="                                                                                              ~~~~~~~">
        <location
            file="$HOME/StudioProjects/Calorie-Tracker/gradle/libs.versions.toml"
            line="36"
            column="95"/>
    </issue>

    <issue
        id="ModifierParameter"
        message="Modifier parameter should be the first optional parameter"
        errorLine1="    modifier: Modifier = Modifier,"
        errorLine2="    ~~~~~~~~">
        <location
            file="src/main/java/com/tenebris/health_tracker/ui/components/GoogleExpressiveComponents.kt"
            line="69"
            column="5"/>
    </issue>

    <issue
        id="ObsoleteSdkInt"
        message="Unnecessary; `SDK_INT` is always >= 34"
        errorLine1="                if (Build.VERSION.SDK_INT >= Build.VERSION_CODES.S) {"
        errorLine2="                    ~~~~~~~~~~~~~~~~~~~~~~~~~~~~~~~~~~~~~~~~~~~~~~">
        <location
            file="src/main/java/com/tenebris/health_tracker/data/service/CoachNotificationDispatcher.kt"
            line="77"
            column="21"/>
    </issue>

    <issue
        id="ObsoleteSdkInt"
        message="Unnecessary; `SDK_INT` is always >= 34"
        errorLine1="            dynamicColor &amp;&amp; Build.VERSION.SDK_INT >= Build.VERSION_CODES.S -> {"
        errorLine2="                            ~~~~~~~~~~~~~~~~~~~~~~~~~~~~~~~~~~~~~~~~~~~~~~">
        <location
            file="src/main/java/com/tenebris/health_tracker/ui/theme/Theme.kt"
            line="107"
            column="29"/>
    </issue>

    <issue
        id="ObsoleteSdkInt"
        message="This folder configuration (`v31`) is unnecessary; `minSdkVersion` is 34. Merge all the resources in this folder into `values`.">
        <location
            file="src/main/res/values-v31"/>
    </issue>

    <issue
        id="AutoboxingStateCreation"
        message="Prefer `mutableIntStateOf` instead of `mutableStateOf`"
        errorLine1="    var baseCalories by remember { mutableStateOf(0) }"
        errorLine2="                                   ~~~~~~~~~~~~~~">
        <location
            file="src/main/java/com/tenebris/health_tracker/ui/dashboard/DashboardScreen.kt"
            line="525"
            column="36"/>
    </issue>

    <issue
        id="AutoboxingStateCreation"
        message="Prefer `mutableIntStateOf` instead of `mutableStateOf`"
        errorLine1="    var baseProtein by remember { mutableStateOf(0) }"
        errorLine2="                                  ~~~~~~~~~~~~~~">
        <location
            file="src/main/java/com/tenebris/health_tracker/ui/dashboard/DashboardScreen.kt"
            line="526"
            column="35"/>
    </issue>

    <issue
        id="AutoboxingStateCreation"
        message="Prefer `mutableIntStateOf` instead of `mutableStateOf`"
        errorLine1="    var baseFat by remember { mutableStateOf(0) }"
        errorLine2="                              ~~~~~~~~~~~~~~">
        <location
            file="src/main/java/com/tenebris/health_tracker/ui/dashboard/DashboardScreen.kt"
            line="527"
            column="31"/>
    </issue>

    <issue
        id="AutoboxingStateCreation"
        message="Prefer `mutableIntStateOf` instead of `mutableStateOf`"
        errorLine1="    var baseCarbs by remember { mutableStateOf(0) }"
        errorLine2="                                ~~~~~~~~~~~~~~">
        <location
            file="src/main/java/com/tenebris/health_tracker/ui/dashboard/DashboardScreen.kt"
            line="528"
            column="33"/>
    </issue>

    <issue
        id="AutoboxingStateCreation"
        message="Prefer `mutableIntStateOf` instead of `mutableStateOf`"
        errorLine1="    var baseFiber by remember { mutableStateOf(0) }"
        errorLine2="                                ~~~~~~~~~~~~~~">
        <location
            file="src/main/java/com/tenebris/health_tracker/ui/dashboard/DashboardScreen.kt"
            line="529"
            column="33"/>
    </issue>

    <issue
        id="AutoboxingStateCreation"
        message="Prefer `mutableFloatStateOf` instead of `mutableStateOf`"
        errorLine1="    var offset by remember(state.offset) { mutableStateOf(state.offset.toFloat()) }"
        errorLine2="                                           ~~~~~~~~~~~~~~">
        <location
            file="src/main/java/com/tenebris/health_tracker/ui/settings/SettingsScreen.kt"
            line="32"
            column="44"/>
    </issue>

    <issue
        id="AutoboxingStateCreation"
        message="Prefer `mutableFloatStateOf` instead of `mutableStateOf`"
        errorLine1="    var activity by remember(state.activityLevel) { mutableStateOf(state.activityLevel) }"
        errorLine2="                                                    ~~~~~~~~~~~~~~">
        <location
            file="src/main/java/com/tenebris/health_tracker/ui/settings/SettingsScreen.kt"
            line="33"
            column="53"/>
    </issue>

    <issue
        id="UnusedResources"
        message="The resource `R.color.expressive_surface` appears to be unused"
        errorLine1="    &lt;color name=&quot;expressive_surface&quot;>#FF1C1B1B&lt;/color>"
        errorLine2="           ~~~~~~~~~~~~~~~~~~~~~~~~~">
        <location
            file="src/main/res/values/colors.xml"
            line="4"
            column="12"/>
    </issue>

    <issue
        id="UnusedResources"
        message="The resource `R.color.expressive_primary` appears to be unused"
        errorLine1="    &lt;color name=&quot;expressive_primary&quot;>#FFFFB5A0&lt;/color>"
        errorLine2="           ~~~~~~~~~~~~~~~~~~~~~~~~~">
        <location
            file="src/main/res/values/colors.xml"
            line="5"
            column="12"/>
    </issue>

    <issue
        id="UnusedResources"
        message="The resource `R.color.expressive_secondary` appears to be unused"
        errorLine1="    &lt;color name=&quot;expressive_secondary&quot;>#FF95CFBD&lt;/color>"
        errorLine2="           ~~~~~~~~~~~~~~~~~~~~~~~~~~~">
        <location
            file="src/main/res/values/colors.xml"
            line="6"
            column="12"/>
    </issue>

    <issue
        id="UnusedResources"
        message="The resource `R.color.expressive_tertiary` appears to be unused"
        errorLine1="    &lt;color name=&quot;expressive_tertiary&quot;>#FFFFB1C2&lt;/color>"
        errorLine2="           ~~~~~~~~~~~~~~~~~~~~~~~~~~">
        <location
            file="src/main/res/values/colors.xml"
            line="7"
            column="12"/>
    </issue>

    <issue
        id="UnusedResources"
        message="The resource `R.drawable.ic_launcher_background` appears to be unused"
        errorLine1="&lt;vector xmlns:android=&quot;http://schemas.android.com/apk/res/android&quot;"
        errorLine2="^">
        <location
            file="src/main/res/drawable/ic_launcher_background.xml"
            line="2"
            column="1"/>
    </issue>

    <issue
        id="MonochromeLauncherIcon"
        message="The application adaptive icon is missing a monochrome tag"
        errorLine1="&lt;adaptive-icon xmlns:android=&quot;http://schemas.android.com/apk/res/android&quot;>"
        errorLine2="^">
        <location
            file="src/main/res/mipmap-anydpi/ic_launcher.xml"
            line="2"
            column="1"/>
    </issue>

    <issue
        id="MonochromeLauncherIcon"
        message="The application adaptive roundIcon is missing a monochrome tag"
        errorLine1="&lt;adaptive-icon xmlns:android=&quot;http://schemas.android.com/apk/res/android&quot;>"
        errorLine2="^">
        <location
            file="src/main/res/mipmap-anydpi/ic_launcher_round.xml"
            line="2"
            column="1"/>
    </issue>

    <issue
        id="IconDipSize"
        message="The image `helix_icon.png` varies significantly in its density-independent (dip) size across the various density versions: mipmap-hdpi/helix_icon.png: 733x651 dp (1099x976 px), mipmap-mdpi/helix_icon.png: 1099x976 dp (1099x976 px), mipmap-xhdpi/helix_icon.png: 550x488 dp (1099x976 px), mipmap-xxhdpi/helix_icon.png: 366x325 dp (1099x976 px), mipmap-xxxhdpi/helix_icon.png: 275x244 dp (1099x976 px)">
        <location
            file="src/main/res/mipmap-xxxhdpi/helix_icon.png"/>
        <location
            file="src/main/res/mipmap-xxhdpi/helix_icon.png"/>
        <location
            file="src/main/res/mipmap-xhdpi/helix_icon.png"/>
        <location
            file="src/main/res/mipmap-hdpi/helix_icon.png"/>
        <location
            file="src/main/res/mipmap-mdpi/helix_icon.png"/>
    </issue>

    <issue
        id="IconDuplicatesConfig"
        message="The `helix_icon.png` icon has identical contents in the following configuration folders: mipmap-hdpi, mipmap-mdpi, mipmap-xhdpi, mipmap-xxhdpi, mipmap-xxxhdpi">
        <location
            file="src/main/res/mipmap-xxxhdpi/helix_icon.png"/>
        <location
            file="src/main/res/mipmap-xxhdpi/helix_icon.png"/>
        <location
            file="src/main/res/mipmap-xhdpi/helix_icon.png"/>
        <location
            file="src/main/res/mipmap-mdpi/helix_icon.png"/>
        <location
            file="src/main/res/mipmap-hdpi/helix_icon.png"/>
    </issue>

    <issue
        id="UseKtx"
        message="Use the KTX extension function `String.toUri` instead?"
        errorLine1="                Uri.parse("
        errorLine2="                ^">
        <location
            file="src/main/java/com/tenebris/health_tracker/data/service/CalendarContextResolver.kt"
            line="33"
            column="17"/>
    </issue>

    <issue
        id="UseKtx"
        message="Use the KTX extension function `SharedPreferences.edit` instead?"
        errorLine1="        prefs.edit().putString(KEY_API_KEY, key).apply()"
        errorLine2="        ~~~~~~~~~~~~">
        <location
            file="src/main/java/com/tenebris/health_tracker/data/pref/EncryptedStorageManager.kt"
            line="27"
            column="9"/>
    </issue>

    <issue
        id="UseKtx"
        message="Use the KTX extension function `SharedPreferences.edit` instead?"
        errorLine1="        prefs.edit().remove(KEY_API_KEY).apply()"
        errorLine2="        ~~~~~~~~~~~~">
        <location
            file="src/main/java/com/tenebris/health_tracker/data/pref/EncryptedStorageManager.kt"
            line="35"
            column="9"/>
    </issue>

</issues>
